demo_it_analyze/__about__.py
demo_it_analyze/__init__.py
demo_it_analyze/app.py
demo_it_analyze/nlp/__init__.py
demo_it_analyze/nlp/ner.py
demo_it_analyze-0.0.1.dev0.dist-info/METADATA
demo_it_analyze-0.0.1.dev0.dist-info/WHEEL
demo_it_analyze-0.0.1.dev0.dist-info/RECORD
