Metadata-Version: 2.1
Name: demo-it-analyze
Version: 0.0.1.dev0
Project-URL: Documentation, https://github.com/unknown/demo-it-analyze#readme
Project-URL: Issues, https://github.com/unknown/demo-it-analyze/issues
Project-URL: Source, https://github.com/unknown/demo-it-analyze
Author-email: Mattia Di Gangi <mattiadg@users.noreply.github.com>
License-Expression: MIT
Classifier: Development Status :: 4 - Beta
Classifier: Programming Language :: Python
Classifier: Programming Language :: Python :: 3.7
Classifier: Programming Language :: Python :: 3.8
Classifier: Programming Language :: Python :: 3.9
Classifier: Programming Language :: Python :: 3.10
Classifier: Programming Language :: Python :: 3.11
Classifier: Programming Language :: Python :: Implementation :: CPython
Classifier: Programming Language :: Python :: Implementation :: PyPy
Requires-Python: >=3.7
Requires-Dist: flask
Requires-Dist: pydantic
Requires-Dist: spacy
